{"stats":{"minecraft:crafted":{"minecraft:crafting_table":1,"minecraft:stick":4,"minecraft:jungle_planks":16},"minecraft:used":{"minecraft:written_book":1},"minecraft:picked_up":{"minecraft:stick":1,"minecraft:jungle_log":4},"minecraft:mined":{"minecraft:vine":1,"minecraft:jungle_log":4,"minecraft:jungle_leaves":1},"minecraft:custom":{"minecraft:time_since_rest":365,"minecraft:crouch_one_cm":386,"minecraft:play_time":3020,"minecraft:sprint_one_cm":1844,"minecraft:deaths":1,"minecraft:damage_taken":250,"minecraft:walk_one_cm":3158,"minecraft:sneak_time":225,"minecraft:walk_under_water_one_cm":138,"minecraft:jump":34,"minecraft:leave_game":1,"minecraft:time_since_death":345,"minecraft:walk_on_water_one_cm":68,"minecraft:total_world_time":3020,"minecraft:climb_one_cm":823,"minecraft:swim_one_cm":2723,"minecraft:fall_one_cm":3257,"minecraft:fly_one_cm":5325}},"DataVersion":3839}